gitsub/__init__.py
gitsub/add.py
gitsub/cache.py
gitsub/display.py
gitsub/env.py
gitsub/fetch.py
gitsub/git.py
gitsub/ls.py
gitsub/main.py
gitsub/repo.py
gitsub/sync.py
gitsub/utils.py
gitsub-0.2.3.dist-info/DESCRIPTION.rst
gitsub-0.2.3.dist-info/METADATA
gitsub-0.2.3.dist-info/RECORD
gitsub-0.2.3.dist-info/WHEEL
gitsub-0.2.3.dist-info/entry_points.txt
gitsub-0.2.3.dist-info/metadata.json
gitsub-0.2.3.dist-info/top_level.txt
