Metadata-Version: 2.0
Name: gitsub
Version: 0.2.3
Summary: Track git repositories updates
Home-page: https://github.com/aufarg/gitsub
Author: Aufar Gilbran
Author-email: aufargilbran@gmail.com
License: MIT
Platform: UNKNOWN
Classifier: Development Status :: 3 - Alpha
Classifier: Intended Audience :: Developers
Classifier: Topic :: Software Development :: Version Control
